subscrypt/__init__.py
subscrypt/client.py
subscrypt-0.1.0.dist-info/LICENSE
subscrypt-0.1.0.dist-info/METADATA
subscrypt-0.1.0.dist-info/WHEEL
subscrypt-0.1.0.dist-info/top_level.txt
subscrypt-0.1.0.dist-info/RECORD
